simplicatus/__init__.py
simplicatus/simparser.py
simplicatus-0.1.0.dist-info/LICENSE
simplicatus-0.1.0.dist-info/METADATA
simplicatus-0.1.0.dist-info/WHEEL
simplicatus-0.1.0.dist-info/top_level.txt
simplicatus-0.1.0.dist-info/RECORD
